LICENSE
README.md
setup.py
src/gat/__init__.py
src/gat/datasets/__init__.py
src/gat/datasets/builder.py
src/gat/datasets/cub.py
src/gat/datasets/env.py
src/gat/datasets/imagenet.py
src/gat/datasets/transforms.py
src/gat/models/__init__.py
src/gat/models/attack/__init__.py
src/gat/models/attack/aim_attack.py
src/gat/models/attack/generator/__init__.py
src/gat/models/attack/generator/aim.py
src/gat/models/attack/generator/cda.py
src/gat/models/attack/loss/__init__.py
src/gat/models/attack/loss/logits.py
src/gat/models/surrogate/__init__.py
src/gat/models/surrogate/builder.py
src/gat/models/surrogate/hooks.py
src/gat/models/surrogate/tv.py
src/gat/runtime/__init__.py
src/gat/runtime/factory.py
src/gat/runtime/meter.py
src/gat/runtime/utils.py
src/pygat.egg-info/PKG-INFO
src/pygat.egg-info/SOURCES.txt
src/pygat.egg-info/dependency_links.txt
src/pygat.egg-info/requires.txt
src/pygat.egg-info/top_level.txt