Metadata-Version: 2.1
Name: pygat
Version: 202411.1
Summary: GAT: Generative Attack Toolbox
Home-page: https://terrytengli.com/gat/
Author: Terry Li
Classifier: Programming Language :: Python :: 3
Classifier: License :: OSI Approved :: MIT License
Requires-Python: >=3.10
License-File: LICENSE
